<?xml version="1.0" encoding="UTF-8" standalone="no"?>
<geometry_complex date="2019/06/30 11:21:43" version="1.00">
  <data_particle aggregation="13.0134 [ms]" algorithm="Filippov Particle-Cluster" brick="0">
    <particle ID="0" type="sphere">
      <radius> 10.0 </radius>
      <position> 0.0 , 0.0 , 0.0 </position>
      <refraction> 1 </refraction>
    </particle>
    <particle ID="1" type="sphere">
      <radius> 10.0 </radius>
      <position> 15.286308523872188 , 1.124116404974175 , -12.84776765127158 </position>
      <refraction> 1 </refraction>
    </particle>
    <particle ID="2" type="sphere">
      <radius> 10.0 </radius>
      <position> 16.818675664930947 , -18.367612147616008 , -17.057799548673785 </position>
      <refraction> 1 </refraction>
    </particle>
    <particle ID="3" type="sphere">
      <radius> 10.0 </radius>
      <position> 31.11406846503472 , 10.823773407957596 , -20.29079585687481 </position>
      <refraction> 1 </refraction>
    </particle>
    <particle ID="4" type="sphere">
      <radius> 10.0 </radius>
      <position> 39.553329328870646 , 18.634212418925568 , -3.9269357337841395 </position>
      <refraction> 1 </refraction>
    </particle>
    <particle ID="5" type="sphere">
      <radius> 10.0 </radius>
      <position> 46.78413922847885 , 10.299855438203346 , 12.754007929978261 </position>
      <refraction> 1 </refraction>
    </particle>
    <particle ID="6" type="sphere">
      <radius> 10.0 </radius>
      <position> -2.7071917647416583 , -21.336453590065688 , -20.208431423146557 </position>
      <refraction> 1 </refraction>
    </particle>
    <particle ID="7" type="sphere">
      <radius> 10.0 </radius>
      <position> -9.29213824225539 , -12.043393453576904 , -36.64855042478042 </position>
      <refraction> 1 </refraction>
    </particle>
    <particle ID="8" type="sphere">
      <radius> 10.0 </radius>
      <position> -25.68166358439262 , -3.6603844035606046 , -28.83135029130633 </position>
      <refraction> 1 </refraction>
    </particle>
    <particle ID="9" type="sphere">
      <radius> 10.0 </radius>
      <position> -36.39864543468107 , 2.0963242114728904 , -12.95663437125954 </position>
      <refraction> 1 </refraction>
    </particle>
    <particle ID="10" type="sphere">
      <radius> 10.0 </radius>
      <position> 34.21866439120259 , 19.529259427880323 , 25.281056413524258 </position>
      <refraction> 1 </refraction>
    </particle>
    <particle ID="11" type="sphere">
      <radius> 10.0 </radius>
      <position> -16.72607078933669 , -17.714218057682544 , -54.328437155043034 </position>
      <refraction> 1 </refraction>
    </particle>
    <particle ID="12" type="sphere">
      <radius> 10.0 </radius>
      <position> 20.96091933915521 , 14.51925864692422 , 39.39247334839415 </position>
      <refraction> 1 </refraction>
    </particle>
    <particle ID="13" type="sphere">
      <radius> 10.0 </radius>
      <position> -34.4667465049626 , -20.589883354992672 , -45.55353123812021 </position>
      <refraction> 1 </refraction>
    </particle>
    <particle ID="14" type="sphere">
      <radius> 10.0 </radius>
      <position> 2.7322711210935857 , 19.031324391259474 , 46.27416256405591 </position>
      <refraction> 1 </refraction>
    </particle>
    <particle ID="15" type="sphere">
      <radius> 10.0 </radius>
      <position> -4.8690051134290115 , -29.841126443378382 , -64.92787516666195 </position>
      <refraction> 1 </refraction>
    </particle>
    <particle ID="16" type="sphere">
      <radius> 10.0 </radius>
      <position> 52.00700465549044 , 14.216167433731854 , 32.720545892220436 </position>
      <refraction> 1 </refraction>
    </particle>
    <particle ID="17" type="sphere">
      <radius> 10.0 </radius>
      <position> -12.987264771988627 , 31.204470054539676 , 48.444580857072864 </position>
      <refraction> 1 </refraction>
    </particle>
    <particle ID="18" type="sphere">
      <radius> 10.0 </radius>
      <position> -0.8846981742522155 , 47.11875688694693 , 47.93139866406036 </position>
      <refraction> 1 </refraction>
    </particle>
    <particle ID="19" type="sphere">
      <radius> 10.0 </radius>
      <position> 71.52941205253985 , 11.136278081499457 , 29.6562530534669 </position>
      <refraction> 1 </refraction>
    </particle>
    <particle ID="20" type="sphere">
      <radius> 10.0 </radius>
      <position> 11.93903292110593 , -40.55245155291039 , -63.26734168987327 </position>
      <refraction> 1 </refraction>
    </particle>
    <particle ID="21" type="sphere">
      <radius> 10.0 </radius>
      <position> -23.758972948387505 , -36.35873700598507 , -64.09729263106955 </position>
      <refraction> 1 </refraction>
    </particle>
    <particle ID="22" type="sphere">
      <radius> 10.0 </radius>
      <position> 64.6083493716775 , 9.603659266233143 , 48.3578564749564 </position>
      <refraction> 1 </refraction>
    </particle>
    <particle ID="23" type="sphere">
      <radius> 10.0 </radius>
      <position> 7.513637042208068 , -31.501413392602405 , -80.54560932023482 </position>
      <refraction> 1 </refraction>
    </particle>
    <particle ID="24" type="sphere">
      <radius> 10.0 </radius>
      <position> 52.13586592696104 , 14.783361118950802 , 63.10939351481188 </position>
      <refraction> 1 </refraction>
    </particle>
    <particle ID="25" type="sphere">
      <radius> 10.0 </radius>
      <position> 13.133836168764628 , -60.148376904422854 , -67.08469082472274 </position>
      <refraction> 1 </refraction>
    </particle>
    <particle ID="26" type="sphere">
      <radius> 10.0 </radius>
      <position> 42.67680519529664 , 1.5244453771434125 , 74.71660347355467 </position>
      <refraction> 1 </refraction>
    </particle>
    <particle ID="27" type="sphere">
      <radius> 10.0 </radius>
      <position> 27.145027216991505 , -72.23271816988094 , -59.49158729651805 </position>
      <refraction> 1 </refraction>
    </particle>
    <particle ID="28" type="sphere">
      <radius> 10.0 </radius>
      <position> 30.730226292902444 , -61.910978300704635 , -76.42601249336151 </position>
      <refraction> 1 </refraction>
    </particle>
    <particle ID="29" type="sphere">
      <radius> 10.0 </radius>
      <position> -15.354792242916096 , 60.91929525204203 , 48.3332917811416 </position>
      <refraction> 1 </refraction>
    </particle>
    <particle ID="30" type="sphere">
      <radius> 10.0 </radius>
      <position> 81.82184084583085 , 16.500241878629193 , 55.85004301425502 </position>
      <refraction> 1 </refraction>
    </particle>
    <particle ID="31" type="sphere">
      <radius> 10.0 </radius>
      <position> 60.74825739011473 , -4.292274112286417 , 81.00853398427178 </position>
      <refraction> 1 </refraction>
    </particle>
    <particle ID="32" type="sphere">
      <radius> 10.0 </radius>
      <position> -34.807803615928535 , -50.643817590562186 , -72.69146584157345 </position>
      <refraction> 1 </refraction>
    </particle>
    <particle ID="33" type="sphere">
      <radius> 10.0 </radius>
      <position> -19.751739733596892 , -54.06840961483449 , -85.4031576817039 </position>
      <refraction> 1 </refraction>
    </particle>
    <particle ID="34" type="sphere">
      <radius> 10.0 </radius>
      <position> 72.68446987049649 , 26.79140430819638 , 70.3621216767824 </position>
      <refraction> 1 </refraction>
    </particle>
    <particle ID="35" type="sphere">
      <radius> 10.0 </radius>
      <position> 78.32518283877414 , 8.9756405129335 , 77.48819473288478 </position>
      <refraction> 1 </refraction>
    </particle>
    <particle ID="36" type="sphere">
      <radius> 10.0 </radius>
      <position> 50.6289327351315 , -3.9722230390568805 , 98.25663055860639 </position>
      <refraction> 1 </refraction>
    </particle>
    <particle ID="37" type="sphere">
      <radius> 10.0 </radius>
      <position> 38.11183604204854 , -87.48485259777492 , -66.35464049375511 </position>
      <refraction> 1 </refraction>
    </particle>
    <particle ID="38" type="sphere">
      <radius> 10.0 </radius>
      <position> -53.47247073949032 , -55.53662024045448 , -67.42927209791087 </position>
      <refraction> 1 </refraction>
    </particle>
    <particle ID="39" type="sphere">
      <radius> 10.0 </radius>
      <position> -40.543702990350695 , -44.3051806424982 , -90.77242653527392 </position>
      <refraction> 1 </refraction>
    </particle>
    <particle ID="40" type="sphere">
      <radius> 10.0 </radius>
      <position> -40.22700957827252 , -64.78901032357595 , -85.75078163083258 </position>
      <refraction> 1 </refraction>
    </particle>
    <particle ID="41" type="sphere">
      <radius> 10.0 </radius>
      <position> 96.22860789387036 , 11.59035128407222 , 68.96583247351943 </position>
      <refraction> 1 </refraction>
    </particle>
    <particle ID="42" type="sphere">
      <radius> 10.0 </radius>
      <position> 69.12357651604367 , 12.720051740800539 , 94.84647302418175 </position>
      <refraction> 1 </refraction>
    </particle>
    <particle ID="43" type="sphere">
      <radius> 10.0 </radius>
      <position> -26.672200157098874 , -50.26370819313946 , -103.89025250512654 </position>
      <refraction> 1 </refraction>
    </particle>
    <particle ID="44" type="sphere">
      <radius> 10.0 </radius>
      <position> 49.74314870490466 , -98.86434211164831 , -77.9830446724259 </position>
      <refraction> 1 </refraction>
    </particle>
    <particle ID="45" type="sphere">
      <radius> 10.0 </radius>
      <position> 70.29922300977759 , -6.479588210689394 , 100.8629306194686 </position>
      <refraction> 1 </refraction>
    </particle>
    <particle ID="46" type="sphere">
      <radius> 10.0 </radius>
      <position> 57.225313619943805 , -18.119243523004645 , 110.76061273426743 </position>
      <refraction> 1 </refraction>
    </particle>
    <particle ID="47" type="sphere">
      <radius> 10.0 </radius>
      <position> -57.4499891691134 , -55.16390031425846 , -89.025874136704 </position>
      <refraction> 1 </refraction>
    </particle>
    <particle ID="48" type="sphere">
      <radius> 10.0 </radius>
      <position> -64.98529088608504 , -37.474354069308866 , -94.5303433465366 </position>
      <refraction> 1 </refraction>
    </particle>
    <particle ID="49" type="sphere">
      <radius> 10.0 </radius>
      <position> -74.13271423716016 , -62.02848229747909 , -80.39081779064507 </position>
      <refraction> 1 </refraction>
    </particle>
    <particle ID="50" type="sphere">
      <radius> 10.0 </radius>
      <position> 110.26164055316708 , 25.63492584400396 , 66.55255266926292 </position>
      <refraction> 1 </refraction>
    </particle>
    <particle ID="51" type="sphere">
      <radius> 10.0 </radius>
      <position> -30.229302378350813 , -44.69072245338559 , -122.76586781515192 </position>
      <refraction> 1 </refraction>
    </particle>
    <particle ID="52" type="sphere">
      <radius> 10.0 </radius>
      <position> -74.14320852478329 , -81.64163999856494 , -76.4762380606785 </position>
      <refraction> 1 </refraction>
    </particle>
    <particle ID="53" type="sphere">
      <radius> 10.0 </radius>
      <position> -68.90122290505843 , -68.43678279324621 , -98.65394955309834 </position>
      <refraction> 1 </refraction>
    </particle>
    <particle ID="54" type="sphere">
      <radius> 10.0 </radius>
      <position> 75.40838119944772 , -25.15477953978992 , 106.30221773654557 </position>
      <refraction> 1 </refraction>
    </particle>
    <particle ID="55" type="sphere">
      <radius> 10.0 </radius>
      <position> -72.73943672906293 , -32.09575618799215 , -112.16394498309754 </position>
      <refraction> 1 </refraction>
    </particle>
    <particle ID="56" type="sphere">
      <radius> 10.0 </radius>
      <position> 88.83162181080571 , 11.384450100518212 , 97.97842425593532 </position>
      <refraction> 1 </refraction>
    </particle>
    <particle ID="57" type="sphere">
      <radius> 10.0 </radius>
      <position> -58.458787605441756 , -30.5188763812448 , -126.07712255988031 </position>
      <refraction> 1 </refraction>
    </particle>
    <particle ID="58" type="sphere">
      <radius> 10.0 </radius>
      <position> -64.33910524107078 , -49.399111360926845 , -123.08403198054583 </position>
      <refraction> 1 </refraction>
    </particle>
    <particle ID="59" type="sphere">
      <radius> 10.0 </radius>
      <position> 113.67404775495515 , 10.015737884762977 , 78.61866730563008 </position>
      <refraction> 1 </refraction>
    </particle>
    <particle ID="60" type="sphere">
      <radius> 10.0 </radius>
      <position> 75.22573937633379 , 8.334249584006631 , 113.38099075375756 </position>
      <refraction> 1 </refraction>
    </particle>
    <particle ID="61" type="sphere">
      <radius> 10.0 </radius>
      <position> 65.09263546945658 , -5.292111166716426 , 123.94709209264248 </position>
      <refraction> 1 </refraction>
    </particle>
    <particle ID="62" type="sphere">
      <radius> 10.0 </radius>
      <position> -48.22098655127999 , -45.43444523531542 , -134.6043281358524 </position>
      <refraction> 1 </refraction>
    </particle>
    <particle ID="63" type="sphere">
      <radius> 10.0 </radius>
      <position> 60.41449430571628 , 14.119235699818724 , 125.51198225066221 </position>
      <refraction> 1 </refraction>
    </particle>
    <particle ID="64" type="sphere">
      <radius> 10.0 </radius>
      <position> -87.95106770579312 , -63.91735284288846 , -102.73784053985761 </position>
      <refraction> 1 </refraction>
    </particle>
    <particle ID="65" type="sphere">
      <radius> 10.0 </radius>
      <position> -98.08113436786296 , -75.34599759991764 , -89.82397868371052 </position>
      <refraction> 1 </refraction>
    </particle>
    <particle ID="66" type="sphere">
      <radius> 10.0 </radius>
      <position> -101.10246934905464 , -49.05421148179123 , -105.21325228291347 </position>
      <refraction> 1 </refraction>
    </particle>
    <particle ID="67" type="sphere">
      <radius> 10.0 </radius>
      <position> 131.8006521372198 , 13.79779277859057 , 71.0607394183756 </position>
      <refraction> 1 </refraction>
    </particle>
    <particle ID="68" type="sphere">
      <radius> 10.0 </radius>
      <position> -114.52324672202505 , -51.88431667832162 , -90.65738614991619 </position>
      <refraction> 1 </refraction>
    </particle>
    <particle ID="69" type="sphere">
      <radius> 10.0 </radius>
      <position> 128.0627977945064 , 33.44407528890373 , 71.288835971683 </position>
      <refraction> 1 </refraction>
    </particle>
    <particle ID="70" type="sphere">
      <radius> 10.0 </radius>
      <position> 120.25378787637456 , 29.43736767238074 , 89.26008127561826 </position>
      <refraction> 1 </refraction>
    </particle>
    <particle ID="71" type="sphere">
      <radius> 10.0 </radius>
      <position> -123.97284300851035 , -35.65385100374465 , -83.78155066549526 </position>
      <refraction> 1 </refraction>
    </particle>
    <particle ID="72" type="sphere">
      <radius> 10.0 </radius>
      <position> 68.52797446765634 , -19.950657190815377 , 137.1124053827553 </position>
      <refraction> 1 </refraction>
    </particle>
    <particle ID="73" type="sphere">
      <radius> 10.0 </radius>
      <position> -129.54795902669733 , -52.02290964853198 , -73.73306818965501 </position>
      <refraction> 1 </refraction>
    </particle>
    <particle ID="74" type="sphere">
      <radius> 10.0 </radius>
      <position> 59.585769834329 , -2.983182710524046 , 143.03487037773593 </position>
      <refraction> 1 </refraction>
    </particle>
    <particle ID="75" type="sphere">
      <radius> 10.0 </radius>
      <position> 146.5916146073735 , 26.704499379866643 , 67.23394526202352 </position>
      <refraction> 1 </refraction>
    </particle>
    <particle ID="76" type="sphere">
      <radius> 10.0 </radius>
      <position> -137.46386459060923 , -32.208150812177735 , -69.42468866639601 </position>
      <refraction> 1 </refraction>
    </particle>
    <particle ID="77" type="sphere">
      <radius> 10.0 </radius>
      <position> -104.93507241676578 , -67.20370335310277 , -112.77494589457385 </position>
      <refraction> 1 </refraction>
    </particle>
    <particle ID="78" type="sphere">
      <radius> 10.0 </radius>
      <position> -143.47489282162098 , -13.547682620249262 , -73.38126118108666 </position>
      <refraction> 1 </refraction>
    </particle>
    <particle ID="79" type="sphere">
      <radius> 10.0 </radius>
      <position> -106.47479435069549 , -86.94805292523446 , -109.98390380609882 </position>
      <refraction> 1 </refraction>
    </particle>
    <particle ID="80" type="sphere">
      <radius> 10.0 </radius>
      <position> -147.6687135255769 , -58.03914610096413 , -67.77965278841152 </position>
      <refraction> 1 </refraction>
    </particle>
    <particle ID="81" type="sphere">
      <radius> 10.0 </radius>
      <position> -142.14658088355546 , -60.238778198300544 , -86.9154136137785 </position>
      <refraction> 1 </refraction>
    </particle>
    <particle ID="82" type="sphere">
      <radius> 10.0 </radius>
      <position> -153.35915993804286 , -36.47951965481652 , -80.78668644970813 </position>
      <refraction> 1 </refraction>
    </particle>
    <particle ID="83" type="sphere">
      <radius> 10.0 </radius>
      <position> -122.3674160533736 , -70.1954144536135 , -122.11106176929925 </position>
      <refraction> 1 </refraction>
    </particle>
    <particle ID="84" type="sphere">
      <radius> 10.0 </radius>
      <position> 153.39806273950026 , 15.600630249315202 , 52.05579142974685 </position>
      <refraction> 1 </refraction>
    </particle>
    <particle ID="85" type="sphere">
      <radius> 10.0 </radius>
      <position> 73.53398361488473 , -38.2033313810032 , 143.57613162422908 </position>
      <refraction> 1 </refraction>
    </particle>
    <particle ID="86" type="sphere">
      <radius> 10.0 </radius>
      <position> -110.99400022682771 , -84.94254412595896 , -129.40267191134157 </position>
      <refraction> 1 </refraction>
    </particle>
    <particle ID="87" type="sphere">
      <radius> 10.0 </radius>
      <position> 150.8166559952969 , 7.843538816020576 , 72.7749321201514 </position>
      <refraction> 1 </refraction>
    </particle>
    <particle ID="88" type="sphere">
      <radius> 10.0 </radius>
      <position> -165.62084763609835 , -49.747181721823566 , -64.78562419587661 </position>
      <refraction> 1 </refraction>
    </particle>
    <particle ID="89" type="sphere">
      <radius> 10.0 </radius>
      <position> 60.976668420441506 , -21.92813991572977 , 155.52618659830043 </position>
      <refraction> 1 </refraction>
    </particle>
    <particle ID="90" type="sphere">
      <radius> 10.0 </radius>
      <position> -155.26375259278385 , -48.5329927073529 , -96.6323897724177 </position>
      <refraction> 1 </refraction>
    </particle>
    <particle ID="91" type="sphere">
      <radius> 10.0 </radius>
      <position> 161.62354009361636 , 32.213391947874754 , 44.54861681849689 </position>
      <refraction> 1 </refraction>
    </particle>
    <particle ID="92" type="sphere">
      <radius> 10.0 </radius>
      <position> -166.8313320056568 , -69.71041343134128 , -64.72153907154045 </position>
      <refraction> 1 </refraction>
    </particle>
    <particle ID="93" type="sphere">
      <radius> 10.0 </radius>
      <position> 72.78733938492277 , 7.640972514882911 , 153.65776483957134 </position>
      <refraction> 1 </refraction>
    </particle>
    <particle ID="94" type="sphere">
      <radius> 10.0 </radius>
      <position> 156.90587890892849 , 42.655949930231884 , 60.9405860513748 </position>
      <refraction> 1 </refraction>
    </particle>
    <particle ID="95" type="sphere">
      <radius> 10.0 </radius>
      <position> 173.0908801430834 , 16.34063212039903 , 48.64326457417937 </position>
      <refraction> 1 </refraction>
    </particle>
    <particle ID="96" type="sphere">
      <radius> 10.0 </radius>
      <position> 88.98703623705389 , -40.75929556074448 , 156.01277953949761 </position>
      <refraction> 1 </refraction>
    </particle>
    <particle ID="97" type="sphere">
      <radius> 10.0 </radius>
      <position> -102.05607132824295 , -99.33209395538056 , -140.0353706426344 </position>
      <refraction> 1 </refraction>
    </particle>
    <particle ID="98" type="sphere">
      <radius> 10.0 </radius>
      <position> 80.42148330497369 , -24.647683167504216 , 164.20101797384473 </position>
      <refraction> 1 </refraction>
    </particle>
    <particle ID="99" type="sphere">
      <radius> 10.0 </radius>
      <position> 70.39945802206823 , -40.72394470666917 , 170.61294621370928 </position>
      <refraction> 1 </refraction>
    </particle>
  </data_particle>
  <data_connector/>
  <software>
    <OS> Windows 10 - 10.0 / amd64 </OS>
    <JVM_compiler> HotSpot 64-Bit Tiered Compilers </JVM_compiler>
    <JVM_vendor> Oracle Corporation / 25.201-b09 </JVM_vendor>
    <JVM_name> Java HotSpot(TM) 64-Bit Server VM </JVM_name>
  </software>
  <hardware>
    <MAC> 00-FF-92-34-28-EB </MAC>
    <IP_local> 10.192.0.106 </IP_local>
    <IP_external> 193.187.117.203 </IP_external>
  </hardware>
  <comments/>
</geometry_complex>
