<?xml version="1.0" encoding="UTF-8" standalone="no"?>
<geometry_complex date="2019/06/30 11:21:46" version="1.00">
  <data_particle aggregation="9.0069 [ms]" algorithm="Filippov Particle-Cluster" brick="0">
    <particle ID="0" type="sphere">
      <radius> 10.0 </radius>
      <position> 0.0 , 0.0 , 0.0 </position>
      <refraction> 1 </refraction>
    </particle>
    <particle ID="1" type="sphere">
      <radius> 10.0 </radius>
      <position> 5.50449960793934 , 14.350844685936114 , -12.796630043348713 </position>
      <refraction> 1 </refraction>
    </particle>
    <particle ID="2" type="sphere">
      <radius> 10.0 </radius>
      <position> -11.877052582195837 , 24.215169876343644 , -13.556058512329527 </position>
      <refraction> 1 </refraction>
    </particle>
    <particle ID="3" type="sphere">
      <radius> 10.0 </radius>
      <position> 0.17480323934420205 , 39.84468766760453 , -16.791942389954126 </position>
      <refraction> 1 </refraction>
    </particle>
    <particle ID="4" type="sphere">
      <radius> 10.0 </radius>
      <position> 18.346084481528266 , -5.444890256477077 , -5.811570690574854 </position>
      <refraction> 1 </refraction>
    </particle>
    <particle ID="5" type="sphere">
      <radius> 10.0 </radius>
      <position> -26.184038382228994 , 36.458471142772154 , -6.81723583940515 </position>
      <refraction> 1 </refraction>
    </particle>
    <particle ID="6" type="sphere">
      <radius> 10.0 </radius>
      <position> -20.147424066592134 , 49.728649813589044 , 6.874427509101652 </position>
      <refraction> 1 </refraction>
    </particle>
    <particle ID="7" type="sphere">
      <radius> 10.0 </radius>
      <position> -33.70915772261778 , 53.96867652464318 , -12.880674302653661 </position>
      <refraction> 1 </refraction>
    </particle>
    <particle ID="8" type="sphere">
      <radius> 10.0 </radius>
      <position> 26.394375704551422 , 0.8129341023594776 , -23.018099750305648 </position>
      <refraction> 1 </refraction>
    </particle>
    <particle ID="9" type="sphere">
      <radius> 10.0 </radius>
      <position> 34.66678862958393 , -1.639465864055495 , 5.104168446341234 </position>
      <refraction> 1 </refraction>
    </particle>
    <particle ID="10" type="sphere">
      <radius> 10.0 </radius>
      <position> 24.53676612826827 , -15.046512351484267 , -35.060825539750674 </position>
      <refraction> 1 </refraction>
    </particle>
    <particle ID="11" type="sphere">
      <radius> 10.0 </radius>
      <position> -28.88713702009091 , 57.74586997569778 , -31.919606141853897 </position>
      <refraction> 1 </refraction>
    </particle>
    <particle ID="12" type="sphere">
      <radius> 10.0 </radius>
      <position> 9.680901114603234 , -27.109687236059017 , -40.873147450994765 </position>
      <refraction> 1 </refraction>
    </particle>
    <particle ID="13" type="sphere">
      <radius> 10.0 </radius>
      <position> -18.634662588841216 , 58.78037287672892 , 24.64456712306233 </position>
      <refraction> 1 </refraction>
    </particle>
    <particle ID="14" type="sphere">
      <radius> 10.0 </radius>
      <position> -15.136182632079292 , 49.20536774580488 , 41.85153996359745 </position>
      <refraction> 1 </refraction>
    </particle>
    <particle ID="15" type="sphere">
      <radius> 10.0 </radius>
      <position> -13.945509830998652 , 78.11503178077302 , 22.5993749370107 </position>
      <refraction> 1 </refraction>
    </particle>
    <particle ID="16" type="sphere">
      <radius> 10.0 </radius>
      <position> -9.122752736801708 , -33.033542686843205 , -37.50706099417889 </position>
      <refraction> 1 </refraction>
    </particle>
    <particle ID="17" type="sphere">
      <radius> 10.0 </radius>
      <position> 36.77292488625328 , -14.3133115806367 , -50.86395292261436 </position>
      <refraction> 1 </refraction>
    </particle>
    <particle ID="18" type="sphere">
      <radius> 10.0 </radius>
      <position> 25.456101216782244 , -30.687474593779825 , -52.81748491700743 </position>
      <refraction> 1 </refraction>
    </particle>
    <particle ID="19" type="sphere">
      <radius> 10.0 </radius>
      <position> 33.53281762326023 , -13.399573369578007 , -70.57858675147233 </position>
      <refraction> 1 </refraction>
    </particle>
    <particle ID="20" type="sphere">
      <radius> 10.0 </radius>
      <position> -33.06582071118736 , 72.33059822440168 , 21.622625287989138 </position>
      <refraction> 1 </refraction>
    </particle>
    <particle ID="21" type="sphere">
      <radius> 10.0 </radius>
      <position> -1.5946948707143196 , 57.97503471905214 , 53.671905862635384 </position>
      <refraction> 1 </refraction>
    </particle>
    <particle ID="22" type="sphere">
      <radius> 10.0 </radius>
      <position> 51.91667890948985 , -10.287504208124709 , -63.343348722008486 </position>
      <refraction> 1 </refraction>
    </particle>
    <particle ID="23" type="sphere">
      <radius> 10.0 </radius>
      <position> 43.20641727900278 , 0.2088382688636976 , -81.58915449247202 </position>
      <refraction> 1 </refraction>
    </particle>
    <particle ID="24" type="sphere">
      <radius> 10.0 </radius>
      <position> 65.54070052062391 , 2.2687805232866367 , -70.87499850695465 </position>
      <refraction> 1 </refraction>
    </particle>
    <particle ID="25" type="sphere">
      <radius> 10.0 </radius>
      <position> 43.178534568111345 , -26.855294531470285 , -81.79926909405822 </position>
      <refraction> 1 </refraction>
    </particle>
    <particle ID="26" type="sphere">
      <radius> 10.0 </radius>
      <position> 28.688173839065563 , -40.32635875213798 , -84.72499538077311 </position>
      <refraction> 1 </refraction>
    </particle>
    <particle ID="27" type="sphere">
      <radius> 10.0 </radius>
      <position> 77.24854402114651 , 14.934737761947456 , -80.99922328694089 </position>
      <refraction> 1 </refraction>
    </particle>
    <particle ID="28" type="sphere">
      <radius> 10.0 </radius>
      <position> 12.65107326878995 , 46.02623011831834 , 61.039684247533216 </position>
      <refraction> 1 </refraction>
    </particle>
    <particle ID="29" type="sphere">
      <radius> 10.0 </radius>
      <position> -30.899746945541533 , 59.174315007881304 , 49.0716597840214 </position>
      <refraction> 1 </refraction>
    </particle>
    <particle ID="30" type="sphere">
      <radius> 10.0 </radius>
      <position> -8.986114791189244 , 91.09291853144913 , 36.98613468080778 </position>
      <refraction> 1 </refraction>
    </particle>
    <particle ID="31" type="sphere">
      <radius> 10.0 </radius>
      <position> 10.704770689488898 , 64.66075034914813 , 68.03729538538684 </position>
      <refraction> 1 </refraction>
    </particle>
    <particle ID="32" type="sphere">
      <radius> 10.0 </radius>
      <position> 7.021707974690002 , 97.289527764505 , 47.25022957071428 </position>
      <refraction> 1 </refraction>
    </particle>
    <particle ID="33" type="sphere">
      <radius> 10.0 </radius>
      <position> 13.62669933956866 , -52.58474915755391 , -79.94128864128635 </position>
      <refraction> 1 </refraction>
    </particle>
    <particle ID="34" type="sphere">
      <radius> 10.0 </radius>
      <position> 0.901042215241965 , 82.01501241791905 , 66.38911588919696 </position>
      <refraction> 1 </refraction>
    </particle>
    <particle ID="35" type="sphere">
      <radius> 10.0 </radius>
      <position> -10.017332855312814 , 96.56383397367816 , 57.69745196307546 </position>
      <refraction> 1 </refraction>
    </particle>
    <particle ID="36" type="sphere">
      <radius> 10.0 </radius>
      <position> 33.22857376201649 , -56.766738506487734 , -74.2799639460461 </position>
      <refraction> 1 </refraction>
    </particle>
    <particle ID="37" type="sphere">
      <radius> 10.0 </radius>
      <position> 51.649406270957584 , -44.60041741393421 , -85.45371105969109 </position>
      <refraction> 1 </refraction>
    </particle>
    <particle ID="38" type="sphere">
      <radius> 10.0 </radius>
      <position> 19.003183720751444 , 81.0819916914975 , 75.87816099696875 </position>
      <refraction> 1 </refraction>
    </particle>
    <particle ID="39" type="sphere">
      <radius> 10.0 </radius>
      <position> 88.35876026461104 , -0.1614327450162385 , -87.97552106213223 </position>
      <refraction> 1 </refraction>
    </particle>
    <particle ID="40" type="sphere">
      <radius> 10.0 </radius>
      <position> -17.762290878423652 , 86.04147823575437 , 72.83996346364466 </position>
      <refraction> 1 </refraction>
    </particle>
    <particle ID="41" type="sphere">
      <radius> 10.0 </radius>
      <position> 52.469267116803046 , -62.19643894910797 , -75.98228804479236 </position>
      <refraction> 1 </refraction>
    </particle>
    <particle ID="42" type="sphere">
      <radius> 10.0 </radius>
      <position> 28.537102899284488 , -61.3712434337461 , -93.16881343771684 </position>
      <refraction> 1 </refraction>
    </particle>
    <particle ID="43" type="sphere">
      <radius> 10.0 </radius>
      <position> 37.39924779521198 , -75.29146568736803 , -80.56008819503859 </position>
      <refraction> 1 </refraction>
    </particle>
    <particle ID="44" type="sphere">
      <radius> 10.0 </radius>
      <position> -25.51511901687051 , 70.01393187115103 , 81.95102339025023 </position>
      <refraction> 1 </refraction>
    </particle>
    <particle ID="45" type="sphere">
      <radius> 10.0 </radius>
      <position> 15.429978714224418 , -57.935263448792256 , -107.87926335403176 </position>
      <refraction> 1 </refraction>
    </particle>
    <particle ID="46" type="sphere">
      <radius> 10.0 </radius>
      <position> 22.002550525672696 , -87.94678655078906 , -78.89138611437164 </position>
      <refraction> 1 </refraction>
    </particle>
    <particle ID="47" type="sphere">
      <radius> 10.0 </radius>
      <position> 11.017087657482406 , -99.2018910397601 , -66.53653977320009 </position>
      <refraction> 1 </refraction>
    </particle>
    <particle ID="48" type="sphere">
      <radius> 10.0 </radius>
      <position> 53.764692472321585 , -83.442606548135 , -88.6675614628576 </position>
      <refraction> 1 </refraction>
    </particle>
    <particle ID="49" type="sphere">
      <radius> 10.0 </radius>
      <position> 14.28539887458747 , -90.50531449222767 , -97.16430336277597 </position>
      <refraction> 1 </refraction>
    </particle>
    <particle ID="50" type="sphere">
      <radius> 10.0 </radius>
      <position> 16.67457505577385 , 114.78235450174077 , 48.15751643603146 </position>
      <refraction> 1 </refraction>
    </particle>
    <particle ID="51" type="sphere">
      <radius> 10.0 </radius>
      <position> 61.33406747597 , -75.39125853263756 , -105.33730521576183 </position>
      <refraction> 1 </refraction>
    </particle>
    <particle ID="52" type="sphere">
      <radius> 10.0 </radius>
      <position> -3.9814125742712143 , -90.88676956887524 , -105.2992951339055 </position>
      <refraction> 1 </refraction>
    </particle>
    <particle ID="53" type="sphere">
      <radius> 10.0 </radius>
      <position> -7.076120188641692 , 70.96553110104766 , 89.63853148574101 </position>
      <refraction> 1 </refraction>
    </particle>
    <particle ID="54" type="sphere">
      <radius> 10.0 </radius>
      <position> 12.06743019478002 , 75.04205807192837 , 93.75027152775422 </position>
      <refraction> 1 </refraction>
    </particle>
    <particle ID="55" type="sphere">
      <radius> 10.0 </radius>
      <position> 3.1313446016117368 , 115.35555846710987 , 62.86303736116502 </position>
      <refraction> 1 </refraction>
    </particle>
    <particle ID="56" type="sphere">
      <radius> 10.0 </radius>
      <position> 80.45527712956688 , -76.1602246058513 , -99.52455783079486 </position>
      <refraction> 1 </refraction>
    </particle>
    <particle ID="57" type="sphere">
      <radius> 10.0 </radius>
      <position> -36.09086703972255 , 91.58483286173018 , 78.61356848911524 </position>
      <refraction> 1 </refraction>
    </particle>
    <particle ID="58" type="sphere">
      <radius> 10.0 </radius>
      <position> 48.80315515889575 , -90.96702565884817 , -106.52158801525813 </position>
      <refraction> 1 </refraction>
    </particle>
    <particle ID="59" type="sphere">
      <radius> 10.0 </radius>
      <position> 16.31680920400475 , 111.17212030718747 , 77.30749539811282 </position>
      <refraction> 1 </refraction>
    </particle>
    <particle ID="60" type="sphere">
      <radius> 10.0 </radius>
      <position> -17.58326929948499 , -102.83396105856258 , -96.79905344701805 </position>
      <refraction> 1 </refraction>
    </particle>
    <particle ID="61" type="sphere">
      <radius> 10.0 </radius>
      <position> 12.349212956981221 , 98.86799395424045 , 92.56746441221372 </position>
      <refraction> 1 </refraction>
    </particle>
    <particle ID="62" type="sphere">
      <radius> 10.0 </radius>
      <position> 15.267223483094327 , 131.24185895527037 , 62.274904575259725 </position>
      <refraction> 1 </refraction>
    </particle>
    <particle ID="63" type="sphere">
      <radius> 10.0 </radius>
      <position> 41.35003271029199 , -106.62707933234582 , -96.56098139169892 </position>
      <refraction> 1 </refraction>
    </particle>
    <particle ID="64" type="sphere">
      <radius> 10.0 </radius>
      <position> -28.814075715011263 , 92.54579378154415 , 97.21799972812916 </position>
      <refraction> 1 </refraction>
    </particle>
    <particle ID="65" type="sphere">
      <radius> 10.0 </radius>
      <position> 92.49850769842617 , -68.2449004734509 , -113.39208251778703 </position>
      <refraction> 1 </refraction>
    </particle>
    <particle ID="66" type="sphere">
      <radius> 10.0 </radius>
      <position> -30.529240257660867 , 109.25043683201007 , 86.35461578259128 </position>
      <refraction> 1 </refraction>
    </particle>
    <particle ID="67" type="sphere">
      <radius> 10.0 </radius>
      <position> 23.612387275641417 , 97.61129940631724 , 109.04659129080451 </position>
      <refraction> 1 </refraction>
    </particle>
    <particle ID="68" type="sphere">
      <radius> 10.0 </radius>
      <position> -33.351924894833004 , -97.1697586347698 , -107.71996509475149 </position>
      <refraction> 1 </refraction>
    </particle>
    <particle ID="69" type="sphere">
      <radius> 10.0 </radius>
      <position> 12.715643564727612 , 129.7629399713908 , 83.74279102858395 </position>
      <refraction> 1 </refraction>
    </particle>
    <particle ID="70" type="sphere">
      <radius> 10.0 </radius>
      <position> -47.68160045669579 , -103.58589440395652 , -95.3307116998485 </position>
      <refraction> 1 </refraction>
    </particle>
    <particle ID="71" type="sphere">
      <radius> 10.0 </radius>
      <position> 1.0910061600388499 , 141.34471125536388 , 72.1220989681825 </position>
      <refraction> 1 </refraction>
    </particle>
    <particle ID="72" type="sphere">
      <radius> 10.0 </radius>
      <position> -6.669767275280556 , 132.47167350857342 , 88.27881882184424 </position>
      <refraction> 1 </refraction>
    </particle>
    <particle ID="73" type="sphere">
      <radius> 10.0 </radius>
      <position> 59.95265725753259 , -113.28238730912686 , -93.45465956539033 </position>
      <refraction> 1 </refraction>
    </particle>
    <particle ID="74" type="sphere">
      <radius> 10.0 </radius>
      <position> -41.28556165454019 , 105.17730176999791 , 106.43250155936025 </position>
      <refraction> 1 </refraction>
    </particle>
    <particle ID="75" type="sphere">
      <radius> 10.0 </radius>
      <position> -5.615859367898279 , -102.97730582266428 , -121.14692954332494 </position>
      <refraction> 1 </refraction>
    </particle>
    <particle ID="76" type="sphere">
      <radius> 10.0 </radius>
      <position> -29.333222110580067 , -95.50407295670493 , -127.24112076632296 </position>
      <refraction> 1 </refraction>
    </particle>
    <particle ID="77" type="sphere">
      <radius> 10.0 </radius>
      <position> 29.121746901063446 , 132.73272423275338 , 94.78906435303294 </position>
      <refraction> 1 </refraction>
    </particle>
    <particle ID="78" type="sphere">
      <radius> 10.0 </radius>
      <position> 33.150193372340816 , -119.90008282892703 , -109.07457450525074 </position>
      <refraction> 1 </refraction>
    </particle>
    <particle ID="79" type="sphere">
      <radius> 10.0 </radius>
      <position> 92.0485547522791 , -75.15326041988996 , -132.15566705797258 </position>
      <refraction> 1 </refraction>
    </particle>
    <particle ID="80" type="sphere">
      <radius> 10.0 </radius>
      <position> 93.20641843854226 , -60.182686806279904 , -145.36707413532494 </position>
      <refraction> 1 </refraction>
    </particle>
    <particle ID="81" type="sphere">
      <radius> 10.0 </radius>
      <position> 6.454216775547436 , 128.11377949787786 , 102.727687359732 </position>
      <refraction> 1 </refraction>
    </particle>
    <particle ID="82" type="sphere">
      <radius> 10.0 </radius>
      <position> 6.425197674829936 , -110.09172529773853 , -135.44371171367536 </position>
      <refraction> 1 </refraction>
    </particle>
    <particle ID="83" type="sphere">
      <radius> 10.0 </radius>
      <position> 16.726046756125232 , 149.2599593989012 , 81.79782334615064 </position>
      <refraction> 1 </refraction>
    </particle>
    <particle ID="84" type="sphere">
      <radius> 10.0 </radius>
      <position> -13.155506917044216 , 129.06851615738114 , 106.88939917126757 </position>
      <refraction> 1 </refraction>
    </particle>
    <particle ID="85" type="sphere">
      <radius> 10.0 </radius>
      <position> 80.83598314782205 , -75.60980264509556 , -148.71072087279097 </position>
      <refraction> 1 </refraction>
    </particle>
    <particle ID="86" type="sphere">
      <radius> 10.0 </radius>
      <position> 99.69909901526201 , -46.04522492114258 , -157.93597504093236 </position>
      <refraction> 1 </refraction>
    </particle>
    <particle ID="87" type="sphere">
      <radius> 10.0 </radius>
      <position> 113.49697963181877 , -56.5136625698414 , -147.9344599913735 </position>
      <refraction> 1 </refraction>
    </particle>
    <particle ID="88" type="sphere">
      <radius> 10.0 </radius>
      <position> -11.498824312659597 , 151.41406571509617 , 83.9586638851246 </position>
      <refraction> 1 </refraction>
    </particle>
    <particle ID="89" type="sphere">
      <radius> 10.0 </radius>
      <position> 41.61277334940745 , -137.61628709110875 , -112.88519732473915 </position>
      <refraction> 1 </refraction>
    </particle>
    <particle ID="90" type="sphere">
      <radius> 10.0 </radius>
      <position> 13.018550937724779 , 165.47501405982976 , 70.69257788737566 </position>
      <refraction> 1 </refraction>
    </particle>
    <particle ID="91" type="sphere">
      <radius> 10.0 </radius>
      <position> -0.2766796911057128 , 146.83645353859455 , 100.6889355062006 </position>
      <refraction> 1 </refraction>
    </particle>
    <particle ID="92" type="sphere">
      <radius> 10.0 </radius>
      <position> 44.01544996759796 , -127.06619031497632 , -129.7055006122141 </position>
      <refraction> 1 </refraction>
    </particle>
    <particle ID="93" type="sphere">
      <radius> 10.0 </radius>
      <position> 28.97771431202262 , -149.96926927067733 , -103.51721387081156 </position>
      <refraction> 1 </refraction>
    </particle>
    <particle ID="94" type="sphere">
      <radius> 10.0 </radius>
      <position> 51.92224190806063 , -118.89367608560318 , -146.15824056581843 </position>
      <refraction> 1 </refraction>
    </particle>
    <particle ID="95" type="sphere">
      <radius> 10.0 </radius>
      <position> 27.37348854191177 , -134.70987428790423 , -137.7441083789843 </position>
      <refraction> 1 </refraction>
    </particle>
    <particle ID="96" type="sphere">
      <radius> 10.0 </radius>
      <position> 70.97011551667234 , -115.78652849438916 , -151.40458638331617 </position>
      <refraction> 1 </refraction>
    </particle>
    <particle ID="97" type="sphere">
      <radius> 10.0 </radius>
      <position> 119.88602883299411 , -70.33886859131192 , -160.89762813688708 </position>
      <refraction> 1 </refraction>
    </particle>
    <particle ID="98" type="sphere">
      <radius> 10.0 </radius>
      <position> 37.67227913870022 , 133.28064874734932 , 112.86081514755885 </position>
      <refraction> 1 </refraction>
    </particle>
    <particle ID="99" type="sphere">
      <radius> 10.0 </radius>
      <position> 35.06635653057546 , -129.04456953339118 , -155.31465486301542 </position>
      <refraction> 1 </refraction>
    </particle>
  </data_particle>
  <data_connector/>
  <software>
    <OS> Windows 10 - 10.0 / amd64 </OS>
    <JVM_compiler> HotSpot 64-Bit Tiered Compilers </JVM_compiler>
    <JVM_vendor> Oracle Corporation / 25.201-b09 </JVM_vendor>
    <JVM_name> Java HotSpot(TM) 64-Bit Server VM </JVM_name>
  </software>
  <hardware>
    <MAC> 00-FF-92-34-28-EB </MAC>
    <IP_local> 10.192.0.106 </IP_local>
    <IP_external> 193.187.117.203 </IP_external>
  </hardware>
  <comments/>
</geometry_complex>
