<?xml version="1.0" encoding="UTF-8" standalone="no"?>
<geometry_complex date="2019/06/30 11:21:44" version="1.00">
  <data_particle aggregation="9.9586 [ms]" algorithm="Filippov Particle-Cluster" brick="0">
    <particle ID="0" type="sphere">
      <radius> 10.0 </radius>
      <position> 0.0 , 0.0 , 0.0 </position>
      <refraction> 1 </refraction>
    </particle>
    <particle ID="1" type="sphere">
      <radius> 10.0 </radius>
      <position> 15.705151924350695 , -12.023955190200395 , -2.9618751184201986 </position>
      <refraction> 1 </refraction>
    </particle>
    <particle ID="2" type="sphere">
      <radius> 10.0 </radius>
      <position> -14.195058737524096 , -14.074438670652796 , 0.6406895849582119 </position>
      <refraction> 1 </refraction>
    </particle>
    <particle ID="3" type="sphere">
      <radius> 10.0 </radius>
      <position> 16.468113698093333 , -31.977156264619154 , -1.827125888140003 </position>
      <refraction> 1 </refraction>
    </particle>
    <particle ID="4" type="sphere">
      <radius> 10.0 </radius>
      <position> -1.0594181538914649 , 14.940890938721711 , -13.253203791250952 </position>
      <refraction> 1 </refraction>
    </particle>
    <particle ID="5" type="sphere">
      <radius> 10.0 </radius>
      <position> -31.655958946293257 , -15.509198918739848 , -9.005989974865166 </position>
      <refraction> 1 </refraction>
    </particle>
    <particle ID="6" type="sphere">
      <radius> 10.0 </radius>
      <position> 29.851215018500298 , -26.029975456487144 , 11.793580374132432 </position>
      <refraction> 1 </refraction>
    </particle>
    <particle ID="7" type="sphere">
      <radius> 10.0 </radius>
      <position> -39.269640047883485 , -3.531291890177023 , 5.085198864207036 </position>
      <refraction> 1 </refraction>
    </particle>
    <particle ID="8" type="sphere">
      <radius> 10.0 </radius>
      <position> 39.33035611101131 , -28.470320291208022 , -5.647480397389479 </position>
      <refraction> 1 </refraction>
    </particle>
    <particle ID="9" type="sphere">
      <radius> 10.0 </radius>
      <position> 39.3205155886239 , -34.109987932850686 , -24.835863644967368 </position>
      <refraction> 1 </refraction>
    </particle>
    <particle ID="10" type="sphere">
      <radius> 10.0 </radius>
      <position> 29.975966985008977 , -43.00856080996212 , -40.11640066908452 </position>
      <refraction> 1 </refraction>
    </particle>
    <particle ID="11" type="sphere">
      <radius> 10.0 </radius>
      <position> 47.254399357845934 , -52.228361069714126 , -21.873087445207986 </position>
      <refraction> 1 </refraction>
    </particle>
    <particle ID="12" type="sphere">
      <radius> 10.0 </radius>
      <position> -30.41081903412382 , 12.360400976081017 , 13.390341108063776 </position>
      <refraction> 1 </refraction>
    </particle>
    <particle ID="13" type="sphere">
      <radius> 10.0 </radius>
      <position> -20.235693598396946 , 29.245778941013167 , 16.759440831819028 </position>
      <refraction> 1 </refraction>
    </particle>
    <particle ID="14" type="sphere">
      <radius> 10.0 </radius>
      <position> 34.49712603059656 , -61.64129417559393 , -34.0652434152608 </position>
      <refraction> 1 </refraction>
    </particle>
    <particle ID="15" type="sphere">
      <radius> 10.0 </radius>
      <position> 64.77530912562563 , -42.857189769330915 , -24.1531902867913 </position>
      <refraction> 1 </refraction>
    </particle>
    <particle ID="16" type="sphere">
      <radius> 10.0 </radius>
      <position> -26.899477030194472 , 18.198586322357848 , 32.19422551512078 </position>
      <refraction> 1 </refraction>
    </particle>
    <particle ID="17" type="sphere">
      <radius> 10.0 </radius>
      <position> -55.521989326262016 , 7.273111212843062 , 0.7118687690691532 </position>
      <refraction> 1 </refraction>
    </particle>
    <particle ID="18" type="sphere">
      <radius> 10.0 </radius>
      <position> 53.400304086489186 , -68.43366692499292 , -11.892310080528015 </position>
      <refraction> 1 </refraction>
    </particle>
    <particle ID="19" type="sphere">
      <radius> 10.0 </radius>
      <position> 44.20100628109421 , -79.53933019796995 , -25.75005747160512 </position>
      <refraction> 1 </refraction>
    </particle>
    <particle ID="20" type="sphere">
      <radius> 10.0 </radius>
      <position> 28.623194211752953 , -91.05124775168086 , -30.73077277855146 </position>
      <refraction> 1 </refraction>
    </particle>
    <particle ID="21" type="sphere">
      <radius> 10.0 </radius>
      <position> 28.72944746396814 , -100.56763619577396 , -13.140233820704683 </position>
      <refraction> 1 </refraction>
    </particle>
    <particle ID="22" type="sphere">
      <radius> 10.0 </radius>
      <position> 45.86880462236055 , -92.86730860210042 , -40.695251899566415 </position>
      <refraction> 1 </refraction>
    </particle>
    <particle ID="23" type="sphere">
      <radius> 10.0 </radius>
      <position> 42.039244696447284 , -107.2807946782836 , 0.19328786034415124 </position>
      <refraction> 1 </refraction>
    </particle>
    <particle ID="24" type="sphere">
      <radius> 10.0 </radius>
      <position> -42.87700283800376 , 7.050777705812614 , 36.71584377738794 </position>
      <refraction> 1 </refraction>
    </particle>
    <particle ID="25" type="sphere">
      <radius> 10.0 </radius>
      <position> 37.22091225934047 , -97.24649067308889 , -58.18915717159623 </position>
      <refraction> 1 </refraction>
    </particle>
    <particle ID="26" type="sphere">
      <radius> 10.0 </radius>
      <position> 56.96797422910589 , -94.20871996171468 , -57.28059112150933 </position>
      <refraction> 1 </refraction>
    </particle>
    <particle ID="27" type="sphere">
      <radius> 10.0 </radius>
      <position> -42.46855146490889 , 28.255126962291392 , 11.987211017557119 </position>
      <refraction> 1 </refraction>
    </particle>
    <particle ID="28" type="sphere">
      <radius> 10.0 </radius>
      <position> -40.35424378553578 , 39.79013094448996 , -4.213819374600295 </position>
      <refraction> 1 </refraction>
    </particle>
    <particle ID="29" type="sphere">
      <radius> 10.0 </radius>
      <position> 62.579813671264034 , -103.95656989556198 , -40.743158450667245 </position>
      <refraction> 1 </refraction>
    </particle>
    <particle ID="30" type="sphere">
      <radius> 10.0 </radius>
      <position> -27.518438441712167 , 40.81561946779343 , 31.357400186880906 </position>
      <refraction> 1 </refraction>
    </particle>
    <particle ID="31" type="sphere">
      <radius> 10.0 </radius>
      <position> -69.372418878122 , 21.554067879401657 , -1.3423652771972563 </position>
      <refraction> 1 </refraction>
    </particle>
    <particle ID="32" type="sphere">
      <radius> 10.0 </radius>
      <position> -78.25229656647512 , 15.997620557080701 , -18.379784829293776 </position>
      <refraction> 1 </refraction>
    </particle>
    <particle ID="33" type="sphere">
      <radius> 10.0 </radius>
      <position> 47.29319235096318 , -116.59341060622029 , -38.16838369096916 </position>
      <refraction> 1 </refraction>
    </particle>
    <particle ID="34" type="sphere">
      <radius> 10.0 </radius>
      <position> -71.705577062444 , 30.456125003191314 , -30.54909510216212 </position>
      <refraction> 1 </refraction>
    </particle>
    <particle ID="35" type="sphere">
      <radius> 10.0 </radius>
      <position> 39.64934521628929 , -117.06368965422708 , -56.64405521323754 </position>
      <refraction> 1 </refraction>
    </particle>
    <particle ID="36" type="sphere">
      <radius> 10.0 </radius>
      <position> 61.900126869508625 , -95.22860790889354 , -76.63604767791665 </position>
      <refraction> 1 </refraction>
    </particle>
    <particle ID="37" type="sphere">
      <radius> 10.0 </radius>
      <position> 59.809558928249736 , -127.21474672309873 , -26.743507919422214 </position>
      <refraction> 1 </refraction>
    </particle>
    <particle ID="38" type="sphere">
      <radius> 10.0 </radius>
      <position> 46.00370845298549 , -136.57624731400773 , -37.77803550065819 </position>
      <refraction> 1 </refraction>
    </particle>
    <particle ID="39" type="sphere">
      <radius> 10.0 </radius>
      <position> 32.45286081924359 , -141.25916721741748 , -51.72238163754684 </position>
      <refraction> 1 </refraction>
    </particle>
    <particle ID="40" type="sphere">
      <radius> 10.0 </radius>
      <position> -57.927713959118506 , 45.57778446456419 , 3.3806662820963513 </position>
      <refraction> 1 </refraction>
    </particle>
    <particle ID="41" type="sphere">
      <radius> 10.0 </radius>
      <position> 61.77637623924193 , -100.55103909636541 , -95.91444002883989 </position>
      <refraction> 1 </refraction>
    </particle>
    <particle ID="42" type="sphere">
      <radius> 10.0 </radius>
      <position> -88.94515886095925 , 16.874084059254344 , -1.5009665270374057 </position>
      <refraction> 1 </refraction>
    </particle>
    <particle ID="43" type="sphere">
      <radius> 10.0 </radius>
      <position> 46.47949760941009 , -112.75636440165546 , -100.04185301717095 </position>
      <refraction> 1 </refraction>
    </particle>
    <particle ID="44" type="sphere">
      <radius> 10.0 </radius>
      <position> -82.93965639485525 , 33.966019121950424 , -9.97443662742734 </position>
      <refraction> 1 </refraction>
    </particle>
    <particle ID="45" type="sphere">
      <radius> 10.0 </radius>
      <position> -93.60600179880048 , 26.8392323063386 , -25.318425190006852 </position>
      <refraction> 1 </refraction>
    </particle>
    <particle ID="46" type="sphere">
      <radius> 10.0 </radius>
      <position> 70.892973344646 , -87.62106663075377 , -108.14977692065716 </position>
      <refraction> 1 </refraction>
    </particle>
    <particle ID="47" type="sphere">
      <radius> 10.0 </radius>
      <position> 55.02160123331555 , -102.20120997188334 , -114.72589810843 </position>
      <refraction> 1 </refraction>
    </particle>
    <particle ID="48" type="sphere">
      <radius> 10.0 </radius>
      <position> 35.75193958429412 , -118.46783937809992 , -115.92576160451867 </position>
      <refraction> 1 </refraction>
    </particle>
    <particle ID="49" type="sphere">
      <radius> 10.0 </radius>
      <position> 41.14819221719953 , -104.52239607810331 , -129.20751857746694 </position>
      <refraction> 1 </refraction>
    </particle>
    <particle ID="50" type="sphere">
      <radius> 10.0 </radius>
      <position> -72.87494949529274 , 45.60799825875165 , 16.66897831006944 </position>
      <refraction> 1 </refraction>
    </particle>
    <particle ID="51" type="sphere">
      <radius> 10.0 </radius>
      <position> 23.734705742138555 , -114.397453817316 , -131.38597026318703 </position>
      <refraction> 1 </refraction>
    </particle>
    <particle ID="52" type="sphere">
      <radius> 10.0 </radius>
      <position> 59.60465429863329 , -98.4324132138695 , -133.9267468777248 </position>
      <refraction> 1 </refraction>
    </particle>
    <particle ID="53" type="sphere">
      <radius> 10.0 </radius>
      <position> 78.02518016975252 , -90.99749159720326 , -131.60163036764266 </position>
      <refraction> 1 </refraction>
    </particle>
    <particle ID="54" type="sphere">
      <radius> 10.0 </radius>
      <position> 33.29895051941659 , -107.34820352943566 , -147.47426699774357 </position>
      <refraction> 1 </refraction>
    </particle>
    <particle ID="55" type="sphere">
      <radius> 10.0 </radius>
      <position> -88.64891061719442 , 46.25238335986587 , -24.68666520225662 </position>
      <refraction> 1 </refraction>
    </particle>
    <particle ID="56" type="sphere">
      <radius> 10.0 </radius>
      <position> 50.39159200580909 , -97.92360082512869 , -151.83528413639726 </position>
      <refraction> 1 </refraction>
    </particle>
    <particle ID="57" type="sphere">
      <radius> 10.0 </radius>
      <position> 70.0116362765286 , -92.38410750597922 , -149.8989954287485 </position>
      <refraction> 1 </refraction>
    </particle>
    <particle ID="58" type="sphere">
      <radius> 10.0 </radius>
      <position> 57.99514856378809 , -83.17456816955826 , -163.0000484865543 </position>
      <refraction> 1 </refraction>
    </particle>
    <particle ID="59" type="sphere">
      <radius> 10.0 </radius>
      <position> 78.67112998205582 , -109.86100131874076 , -145.47504346004501 </position>
      <refraction> 1 </refraction>
    </particle>
    <particle ID="60" type="sphere">
      <radius> 10.0 </radius>
      <position> 89.91902278224359 , -94.14680798593437 , -150.66636048532428 </position>
      <refraction> 1 </refraction>
    </particle>
    <particle ID="61" type="sphere">
      <radius> 10.0 </radius>
      <position> 80.20009105180361 , -84.03723337048305 , -164.94974561132716 </position>
      <refraction> 1 </refraction>
    </particle>
    <particle ID="62" type="sphere">
      <radius> 10.0 </radius>
      <position> 107.83377138019745 , -99.33812396801923 , -143.44749487871678 </position>
      <refraction> 1 </refraction>
    </particle>
    <particle ID="63" type="sphere">
      <radius> 10.0 </radius>
      <position> -68.47575890890803 , 61.30669302103432 , -3.0489669080180306 </position>
      <refraction> 1 </refraction>
    </particle>
    <particle ID="64" type="sphere">
      <radius> 10.0 </radius>
      <position> 55.5492510307169 , -91.78221212501737 , -180.88652523279376 </position>
      <refraction> 1 </refraction>
    </particle>
    <particle ID="65" type="sphere">
      <radius> 10.0 </radius>
      <position> 73.21155280245755 , -99.60268878125999 , -175.38415649994676 </position>
      <refraction> 1 </refraction>
    </particle>
    <particle ID="66" type="sphere">
      <radius> 10.0 </radius>
      <position> -111.26229082420726 , 23.17970655574414 , -16.666065469558554 </position>
      <refraction> 1 </refraction>
    </particle>
    <particle ID="67" type="sphere">
      <radius> 10.0 </radius>
      <position> -106.95273338481331 , 40.86154173503361 , -30.67906858216802 </position>
      <refraction> 1 </refraction>
    </particle>
    <particle ID="68" type="sphere">
      <radius> 10.0 </radius>
      <position> 75.05413483506445 , -81.73930668960652 , -184.18781887992884 </position>
      <refraction> 1 </refraction>
    </particle>
    <particle ID="69" type="sphere">
      <radius> 10.0 </radius>
      <position> -98.97810754097658 , 57.34776805059273 , -38.71708351889073 </position>
      <refraction> 1 </refraction>
    </particle>
    <particle ID="70" type="sphere">
      <radius> 10.0 </radius>
      <position> 110.7055546763283 , -91.48275543722389 , -161.6146643210227 </position>
      <refraction> 1 </refraction>
    </particle>
    <particle ID="71" type="sphere">
      <radius> 10.0 </radius>
      <position> 107.45933536217257 , -111.1330170079589 , -159.59494964548406 </position>
      <refraction> 1 </refraction>
    </particle>
    <particle ID="72" type="sphere">
      <radius> 10.0 </radius>
      <position> -92.70420961446119 , 43.37588649607832 , 18.017355039804457 </position>
      <refraction> 1 </refraction>
    </particle>
    <particle ID="73" type="sphere">
      <radius> 10.0 </radius>
      <position> -88.69561885956432 , 37.125003631971225 , 36.58769868710861 </position>
      <refraction> 1 </refraction>
    </particle>
    <particle ID="74" type="sphere">
      <radius> 10.0 </radius>
      <position> -121.54087458896986 , 44.31640122767034 , -43.91727396257095 </position>
      <refraction> 1 </refraction>
    </particle>
    <particle ID="75" type="sphere">
      <radius> 10.0 </radius>
      <position> 98.36088984835123 , -101.11843821694333 , -174.32337456027318 </position>
      <refraction> 1 </refraction>
    </particle>
    <particle ID="76" type="sphere">
      <radius> 10.0 </radius>
      <position> -128.78401507567133 , 25.63155270556623 , -7.339885688251627 </position>
      <refraction> 1 </refraction>
    </particle>
    <particle ID="77" type="sphere">
      <radius> 10.0 </radius>
      <position> -106.05944503018098 , 69.7929792037003 , -24.753868333319925 </position>
      <refraction> 1 </refraction>
    </particle>
    <particle ID="78" type="sphere">
      <radius> 10.0 </radius>
      <position> -124.14435172881898 , 54.423817380238944 , -26.856733376145236 </position>
      <refraction> 1 </refraction>
    </particle>
    <particle ID="79" type="sphere">
      <radius> 10.0 </radius>
      <position> 109.1696467591358 , -79.04224729369952 , -177.1991034704053 </position>
      <refraction> 1 </refraction>
    </particle>
    <particle ID="80" type="sphere">
      <radius> 10.0 </radius>
      <position> 125.84720616039077 , -79.1632995707084 , -166.16079026757166 </position>
      <refraction> 1 </refraction>
    </particle>
    <particle ID="81" type="sphere">
      <radius> 10.0 </radius>
      <position> -102.37304197130558 , 30.583604698140178 , 49.631402019018665 </position>
      <refraction> 1 </refraction>
    </particle>
    <particle ID="82" type="sphere">
      <radius> 10.0 </radius>
      <position> 140.27707746596508 , -69.75839041109722 , -155.99582605691006 </position>
      <refraction> 1 </refraction>
    </particle>
    <particle ID="83" type="sphere">
      <radius> 10.0 </radius>
      <position> -99.08009098099397 , 85.06508527309538 , -13.888722551451849 </position>
      <refraction> 1 </refraction>
    </particle>
    <particle ID="84" type="sphere">
      <radius> 10.0 </radius>
      <position> -124.69483609824309 , 60.63111373184093 , -7.852353918704161 </position>
      <refraction> 1 </refraction>
    </particle>
    <particle ID="85" type="sphere">
      <radius> 10.0 </radius>
      <position> 126.19711338806262 , -104.12804864025176 , -161.28577514460645 </position>
      <refraction> 1 </refraction>
    </particle>
    <particle ID="86" type="sphere">
      <radius> 10.0 </radius>
      <position> 94.20060447070627 , -102.11093985583446 , -193.86069693754263 </position>
      <refraction> 1 </refraction>
    </particle>
    <particle ID="87" type="sphere">
      <radius> 10.0 </radius>
      <position> 121.88114994472542 , -96.62858004492809 , -179.31714863481875 </position>
      <refraction> 1 </refraction>
    </particle>
    <particle ID="88" type="sphere">
      <radius> 10.0 </radius>
      <position> 153.84264590658086 , -83.92663126928761 , -152.09245527420524 </position>
      <refraction> 1 </refraction>
    </particle>
    <particle ID="89" type="sphere">
      <radius> 10.0 </radius>
      <position> 145.70330011981375 , -99.69224099555646 , -161.32265569036176 </position>
      <refraction> 1 </refraction>
    </particle>
    <particle ID="90" type="sphere">
      <radius> 10.0 </radius>
      <position> 101.03812817963576 , -120.8001924576655 , -195.85069852416984 </position>
      <refraction> 1 </refraction>
    </particle>
    <particle ID="91" type="sphere">
      <radius> 10.0 </radius>
      <position> -147.79838606417843 , 20.92659300842582 , -11.379322500445213 </position>
      <refraction> 1 </refraction>
    </particle>
    <particle ID="92" type="sphere">
      <radius> 10.0 </radius>
      <position> -119.09278388060078 , 34.034737931749646 , 39.21315315030593 </position>
      <refraction> 1 </refraction>
    </particle>
    <particle ID="93" type="sphere">
      <radius> 10.0 </radius>
      <position> 145.50003571357627 , -85.95058861815284 , -175.85281993994113 </position>
      <refraction> 1 </refraction>
    </particle>
    <particle ID="94" type="sphere">
      <radius> 10.0 </radius>
      <position> 168.06383928501484 , -70.22433398127983 , -155.255477171733 </position>
      <refraction> 1 </refraction>
    </particle>
    <particle ID="95" type="sphere">
      <radius> 10.0 </radius>
      <position> 164.13961862158646 , -101.01775310791733 , -153.45843726660203 </position>
      <refraction> 1 </refraction>
    </particle>
    <particle ID="96" type="sphere">
      <radius> 10.0 </radius>
      <position> -93.45859924502264 , 34.01049800642809 , 67.20379834773365 </position>
      <refraction> 1 </refraction>
    </particle>
    <particle ID="97" type="sphere">
      <radius> 10.0 </radius>
      <position> -120.29432956802451 , 66.89126369156037 , 10.625905316389613 </position>
      <refraction> 1 </refraction>
    </particle>
    <particle ID="98" type="sphere">
      <radius> 10.0 </radius>
      <position> -130.80229398080292 , 74.77037232144798 , -20.61089319046212 </position>
      <refraction> 1 </refraction>
    </particle>
    <particle ID="99" type="sphere">
      <radius> 10.0 </radius>
      <position> -113.10382778741246 , 47.05781618360517 , 53.2989067976134 </position>
      <refraction> 1 </refraction>
    </particle>
  </data_particle>
  <data_connector/>
  <software>
    <OS> Windows 10 - 10.0 / amd64 </OS>
    <JVM_compiler> HotSpot 64-Bit Tiered Compilers </JVM_compiler>
    <JVM_vendor> Oracle Corporation / 25.201-b09 </JVM_vendor>
    <JVM_name> Java HotSpot(TM) 64-Bit Server VM </JVM_name>
  </software>
  <hardware>
    <MAC> 00-FF-92-34-28-EB </MAC>
    <IP_local> 10.192.0.106 </IP_local>
    <IP_external> 193.187.117.203 </IP_external>
  </hardware>
  <comments/>
</geometry_complex>
